{
    "key": "group_641ad00054827",
    "title": "Block - Hero",
    "fields": [
        {
            "key": "field_641ad1a71a01b",
            "label": "General",
            "name": "",
            "aria-label": "",
            "type": "tab",
            "instructions": "",
            "required": 0,
            "conditional_logic": 0,
            "wrapper": {
                "width": "",
                "class": "",
                "id": ""
            },
            "placement": "top",
            "endpoint": 0
        },
        {
            "key": "field_641ad000300fa",
            "label": "Title",
            "name": "header",
            "aria-label": "",
            "type": "clone",
            "instructions": "",
            "required": 0,
            "conditional_logic": 0,
            "wrapper": {
                "width": "",
                "class": "",
                "id": ""
            },
            "clone": [
                "group_6412dea7868f3"
            ],
            "display": "seamless",
            "layout": "block",
            "prefix_label": 0,
            "prefix_name": 0
        },
        {
            "key": "field_641ad1231a018",
            "label": "Description",
            "name": "description",
            "aria-label": "",
            "type": "wysiwyg",
            "instructions": "",
            "required": 0,
            "conditional_logic": 0,
            "wrapper": {
                "width": "",
                "class": "",
                "id": ""
            },
            "default_value": "",
            "tabs": "all",
            "toolbar": "full",
            "media_upload": 1,
            "delay": 0
        },
        {
            "key": "field_641ad19d1a01a",
            "label": "Image",
            "name": "image",
            "aria-label": "",
            "type": "image",
            "instructions": "",
            "required": 0,
            "conditional_logic": [
                [
                    {
                        "field": "field_64215a2971632",
                        "operator": "==",
                        "value": "1"
                    }
                ]
            ],
            "wrapper": {
                "width": "",
                "class": "",
                "id": ""
            },
            "return_format": "array",
            "library": "all",
            "min_width": "",
            "min_height": "",
            "min_size": "",
            "max_width": "",
            "max_height": "",
            "max_size": "",
            "mime_types": "",
            "preview_size": "medium"
        },
        {
            "key": "field_643433426912a",
            "label": "Mobile image",
            "name": "mobile_image",
            "aria-label": "",
            "type": "image",
            "instructions": "",
            "required": 0,
            "conditional_logic": [
                [
                    {
                        "field": "field_64215a2971632",
                        "operator": "==",
                        "value": "1"
                    }
                ]
            ],
            "wrapper": {
                "width": "",
                "class": "",
                "id": ""
            },
            "return_format": "array",
            "library": "all",
            "min_width": "",
            "min_height": "",
            "min_size": "",
            "max_width": "",
            "max_height": "",
            "max_size": "",
            "mime_types": "",
            "preview_size": "medium"
        },
        {
            "key": "field_641c0d59df983",
            "label": "Video",
            "name": "video",
            "aria-label": "",
            "type": "file",
            "instructions": "Under customisation tab, video can be cropped",
            "required": 0,
            "conditional_logic": [
                [
                    {
                        "field": "field_64215a2971632",
                        "operator": "==",
                        "value": "1"
                    }
                ]
            ],
            "wrapper": {
                "width": "",
                "class": "",
                "id": ""
            },
            "return_format": "array",
            "library": "all",
            "min_size": "",
            "max_size": "",
            "mime_types": ""
        },
        {
            "key": "field_64215f1ead4ba",
            "label": "Button",
            "name": "button",
            "aria-label": "",
            "type": "clone",
            "instructions": "",
            "required": 0,
            "conditional_logic": [
                [
                    {
                        "field": "field_64215a2971632",
                        "operator": "!=",
                        "value": "1"
                    }
                ]
            ],
            "wrapper": {
                "width": "",
                "class": "",
                "id": ""
            },
            "clone": [
                "group_6412dd26973d5"
            ],
            "display": "seamless",
            "layout": "block",
            "prefix_label": 0,
            "prefix_name": 0
        },
        {
            "key": "field_641ad2b7b9343",
            "label": "Additional",
            "name": "",
            "aria-label": "",
            "type": "tab",
            "instructions": "",
            "required": 0,
            "conditional_logic": [
                [
                    {
                        "field": "field_64215a2971632",
                        "operator": "==",
                        "value": "1"
                    }
                ]
            ],
            "wrapper": {
                "width": "",
                "class": "",
                "id": ""
            },
            "placement": "top",
            "endpoint": 0
        },
        {
            "key": "field_641ad1651a019",
            "label": "Label text",
            "name": "label_text",
            "aria-label": "",
            "type": "text",
            "instructions": "",
            "required": 0,
            "conditional_logic": 0,
            "wrapper": {
                "width": "",
                "class": "",
                "id": ""
            },
            "default_value": "",
            "disabled": 0,
            "maxlength": 60,
            "placeholder": "",
            "prepend": "",
            "append": ""
        },
        {
            "key": "field_641ad2c7b9344",
            "label": "Checking list",
            "name": "list",
            "aria-label": "",
            "type": "repeater",
            "instructions": "",
            "required": 0,
            "conditional_logic": [
                [
                    {
                        "field": "field_64215a2971632",
                        "operator": "==",
                        "value": "1"
                    }
                ]
            ],
            "wrapper": {
                "width": "",
                "class": "",
                "id": ""
            },
            "layout": "table",
            "pagination": 0,
            "min": 0,
            "max": 0,
            "collapsed": "",
            "button_label": "Add Row",
            "rows_per_page": 20,
            "sub_fields": [
                {
                    "key": "field_641ad2e1b9345",
                    "label": "Title",
                    "name": "title",
                    "aria-label": "",
                    "type": "text",
                    "instructions": "",
                    "required": 0,
                    "conditional_logic": 0,
                    "wrapper": {
                        "width": "",
                        "class": "",
                        "id": ""
                    },
                    "default_value": "",
                    "maxlength": "",
                    "placeholder": "",
                    "prepend": "",
                    "append": "",
                    "parent_repeater": "field_641ad2c7b9344"
                }
            ]
        },
        {
            "key": "field_641ad3fcb6188",
            "label": "Customization",
            "name": "",
            "aria-label": "",
            "type": "tab",
            "instructions": "",
            "required": 0,
            "conditional_logic": 0,
            "wrapper": {
                "width": "",
                "class": "",
                "id": ""
            },
            "placement": "top",
            "endpoint": 0
        },
        {
            "key": "field_64412129ef80e",
            "label": "Enable animations",
            "name": "enable_animations",
            "aria-label": "",
            "type": "true_false",
            "instructions": "",
            "required": 0,
            "conditional_logic": 0,
            "wrapper": {
                "width": "",
                "class": "",
                "id": ""
            },
            "message": "",
            "default_value": 0,
            "ui_on_text": "",
            "ui_off_text": "",
            "ui": 1
        },
        {
            "key": "field_641ad405b6189",
            "label": "Has dotted line",
            "name": "has_dotted_line",
            "aria-label": "",
            "type": "true_false",
            "instructions": "",
            "required": 0,
            "conditional_logic": 0,
            "wrapper": {
                "width": "",
                "class": "",
                "id": ""
            },
            "message": "",
            "default_value": 0,
            "ui_on_text": "",
            "ui_off_text": "",
            "ui": 1
        },
        {
            "key": "field_642157e3dde2f",
            "label": "Has search field",
            "name": "has_search_field",
            "aria-label": "",
            "type": "true_false",
            "instructions": "",
            "required": 0,
            "conditional_logic": [
                [
                    {
                        "field": "field_64215a2971632",
                        "operator": "==",
                        "value": "1"
                    }
                ]
            ],
            "wrapper": {
                "width": "",
                "class": "",
                "id": ""
            },
            "message": "",
            "default_value": 0,
            "ui_on_text": "",
            "ui_off_text": "",
            "ui": 1
        },
        {
            "key": "field_642157fddde30",
            "label": "Has Hexagon",
            "name": "has_hexagon",
            "aria-label": "",
            "type": "true_false",
            "instructions": "",
            "required": 0,
            "conditional_logic": [
                [
                    {
                        "field": "field_64215a2971632",
                        "operator": "==",
                        "value": "1"
                    }
                ]
            ],
            "wrapper": {
                "width": "",
                "class": "",
                "id": ""
            },
            "message": "Text label is disabled if this is checked",
            "default_value": 0,
            "ui_on_text": "",
            "ui_off_text": "",
            "ui": 1
        },
        {
            "key": "field_65423cd1c5bce",
            "label": "Hexagon placement",
            "name": "hexagon_placement",
            "aria-label": "",
            "type": "button_group",
            "instructions": "",
            "required": 0,
            "conditional_logic": [
                [
                    {
                        "field": "field_642157fddde30",
                        "operator": "==",
                        "value": "1"
                    }
                ]
            ],
            "wrapper": {
                "width": "",
                "class": "",
                "id": ""
            },
            "choices": {
                "left": "Left",
                "right": "Right"
            },
            "default_value": "left",
            "return_format": "value",
            "allow_null": 0,
            "layout": "horizontal"
        },
        {
            "key": "field_64215a2971632",
            "label": "Has image field",
            "name": "has_image_field",
            "aria-label": "",
            "type": "true_false",
            "instructions": "",
            "required": 0,
            "conditional_logic": 0,
            "wrapper": {
                "width": "",
                "class": "",
                "id": ""
            },
            "message": "Image\/video\/search\/list\/hexagon is disabled if this is not checked",
            "default_value": 0,
            "ui_on_text": "",
            "ui_off_text": "",
            "ui": 1
        },
        {
            "key": "field_64ef59f0d2c20",
            "label": "Background position",
            "name": "background_position",
            "aria-label": "",
            "type": "select",
            "instructions": "",
            "required": 0,
            "conditional_logic": 0,
            "wrapper": {
                "width": "",
                "class": "",
                "id": ""
            },
            "choices": {
                "center": "Center",
                "top-left": "Top left",
                "top-right": "Top right",
                "top-center": "Top center",
                "bottom-left": "Bottom left",
                "bottom-right": "Bottom right",
                "bottom-center": "Bottom center"
            },
            "default_value": "center",
            "return_format": "value",
            "multiple": 0,
            "allow_null": 0,
            "ui": 0,
            "ajax": 0,
            "placeholder": ""
        },
        {
            "key": "field_642d6e5e05a38",
            "label": "Container spacing",
            "name": "container_spacing",
            "aria-label": "",
            "type": "select",
            "instructions": "",
            "required": 0,
            "conditional_logic": 0,
            "wrapper": {
                "width": "",
                "class": "",
                "id": ""
            },
            "choices": {
                "wide": "Wide",
                "medium": "Medium",
                "narrow": "Narrow"
            },
            "default_value": "wide",
            "return_format": "value",
            "multiple": 0,
            "allow_null": 0,
            "ui": 0,
            "ajax": 0,
            "placeholder": ""
        },
        {
            "key": "field_6463405921241",
            "label": "Crop video",
            "name": "crop_video",
            "aria-label": "",
            "type": "true_false",
            "instructions": "Activate this setting to automatically crop the video. This makes the video height adapt to the size of the hero header. Activating this setting can cause the edges of the video to be cropped out.",
            "required": 0,
            "conditional_logic": 0,
            "wrapper": {
                "width": "",
                "class": "",
                "id": ""
            },
            "message": "",
            "default_value": 0,
            "ui_on_text": "",
            "ui_off_text": "",
            "ui": 1
        },
        {
            "key": "field_6425b2ffb5668",
            "label": "Styling",
            "name": "",
            "aria-label": "",
            "type": "tab",
            "instructions": "",
            "required": 0,
            "conditional_logic": 0,
            "wrapper": {
                "width": "",
                "class": "",
                "id": ""
            },
            "placement": "top",
            "endpoint": 0
        },
        {
            "key": "field_65e71b51aa8f2",
            "label": "Image\/video position",
            "name": "block_layout",
            "aria-label": "",
            "type": "button_group",
            "instructions": "",
            "required": 0,
            "conditional_logic": 0,
            "wrapper": {
                "width": "",
                "class": "",
                "id": ""
            },
            "choices": {
                "left": "Left",
                "right": "Right"
            },
            "default_value": "right",
            "return_format": "value",
            "allow_null": 0,
            "layout": "horizontal"
        },
        {
            "key": "field_65f9971395a98",
            "label": "Image\/video position on mobile",
            "name": "block_layout_mobile",
            "aria-label": "",
            "type": "button_group",
            "instructions": "",
            "required": 0,
            "conditional_logic": 0,
            "wrapper": {
                "width": "",
                "class": "",
                "id": ""
            },
            "choices": {
                "top": "Top",
                "bottom": "Bottom"
            },
            "default_value": "top",
            "return_format": "value",
            "allow_null": 0,
            "layout": "horizontal"
        },
        {
            "key": "field_6425b309b5669",
            "label": "Background color",
            "name": "background_color_clone",
            "aria-label": "",
            "type": "clone",
            "instructions": "",
            "required": 0,
            "conditional_logic": 0,
            "wrapper": {
                "width": "",
                "class": "",
                "id": ""
            },
            "clone": [
                "field_641826f60f389"
            ],
            "display": "seamless",
            "layout": "block",
            "prefix_label": 0,
            "prefix_name": 0
        },
        {
            "key": "field_6425b320b566a",
            "label": "Text color",
            "name": "text_color_clone",
            "aria-label": "",
            "type": "clone",
            "instructions": "",
            "required": 0,
            "conditional_logic": 0,
            "wrapper": {
                "width": "",
                "class": "",
                "id": ""
            },
            "clone": [
                "field_6425926439880"
            ],
            "display": "seamless",
            "layout": "block",
            "prefix_label": 0,
            "prefix_name": 0
        },
        {
            "key": "field_645e60862b051",
            "label": "Hexagon background",
            "name": "hexagon_background",
            "aria-label": "",
            "type": "select",
            "instructions": "",
            "required": 0,
            "conditional_logic": 0,
            "wrapper": {
                "width": "",
                "class": "",
                "id": ""
            },
            "choices": {
                "bg-none": "None",
                "bg-primary": "Dark blue",
                "bg-secondary": "Light blue",
                "bg-gray": "Gray",
                "bg-yellow": "Yellow",
                "bg-red": "Red",
                "bg-light-gray": "Light gray"
            },
            "default_value": "bg-primary",
            "return_format": "value",
            "multiple": 0,
            "allow_null": 0,
            "ui": 0,
            "ajax": 0,
            "placeholder": ""
        },
        {
            "key": "field_645e63e721f32",
            "label": "Hexagon text color",
            "name": "hexagon_text_color",
            "aria-label": "",
            "type": "select",
            "instructions": "",
            "required": 0,
            "conditional_logic": 0,
            "wrapper": {
                "width": "",
                "class": "",
                "id": ""
            },
            "choices": {
                "text-white": "White",
                "text-primary": "Dark blue",
                "text-secondary": "Light blue",
                "text-grey": "Grey",
                "text-yellow": "Yellow",
                "text-red": "Red"
            },
            "default_value": "text-white",
            "return_format": "value",
            "multiple": 0,
            "allow_null": 0,
            "ui": 0,
            "ajax": 0,
            "placeholder": ""
        }
    ],
    "location": [
        [
            {
                "param": "block",
                "operator": "==",
                "value": "acf\/hero"
            }
        ]
    ],
    "menu_order": 0,
    "position": "acf_after_title",
    "style": "default",
    "label_placement": "top",
    "instruction_placement": "label",
    "hide_on_screen": "",
    "active": true,
    "description": "",
    "show_in_rest": 0,
    "modified": 1712581835
}